sentinel_csrf/__init__.py
sentinel_csrf/cli.py
sentinel_csrf/analysis/__init__.py
sentinel_csrf/analysis/browser.py
sentinel_csrf/analysis/headers.py
sentinel_csrf/analysis/samesite.py
sentinel_csrf/analysis/state_change.py
sentinel_csrf/analysis/tokens.py
sentinel_csrf/core/__init__.py
sentinel_csrf/core/detector.py
sentinel_csrf/core/scanner.py
sentinel_csrf/core/verifier.py
sentinel_csrf/input/__init__.py
sentinel_csrf/input/burp.py
sentinel_csrf/input/cookies.py
sentinel_csrf/input/requests.py
sentinel_csrf/output/__init__.py
sentinel_csrf/output/poc.py
sentinel_csrf/utils/__init__.py
sentinel_csrf/utils/cache.py
sentinel_csrf-1.0.8.dist-info/METADATA
sentinel_csrf-1.0.8.dist-info/WHEEL
sentinel_csrf-1.0.8.dist-info/entry_points.txt
sentinel_csrf-1.0.8.dist-info/top_level.txt
sentinel_csrf-1.0.8.dist-info/RECORD
