Metadata-Version: 2.4
Name: sentinel-csrf
Version: 1.0.8
Summary: A verification-driven CSRF exploitation assistant for VAPT teams
Author-email: N15H <nisanthsmpupi@gmail.com>
License: MIT
Project-URL: Homepage, https://github.com/NI54NTH/sentinel-csrf
Project-URL: Documentation, https://github.com/NI54NTH/sentinel-csrf#readme
Project-URL: Repository, https://github.com/NI54NTH/sentinel-csrf
Keywords: csrf,security,vapt,penetration-testing,bug-bounty
Classifier: Development Status :: 4 - Beta
Classifier: Environment :: Console
Classifier: Intended Audience :: Developers
Classifier: Intended Audience :: Information Technology
Classifier: License :: OSI Approved :: MIT License
Classifier: Operating System :: OS Independent
Classifier: Programming Language :: Python :: 3
Classifier: Programming Language :: Python :: 3.10
Classifier: Programming Language :: Python :: 3.11
Classifier: Programming Language :: Python :: 3.12
Classifier: Topic :: Security
Requires-Python: >=3.10
Requires-Dist: requests>=2.28.0
Provides-Extra: dev
Requires-Dist: pytest>=7.0.0; extra == "dev"
Requires-Dist: pytest-cov>=4.0.0; extra == "dev"
